beetsplug/__init__.py
beetsplug/beetmatch/__init__.py
beetsplug/beetmatch/common/__init__.py
beetsplug/beetmatch/common/base_config.py
beetsplug/beetmatch/common/helpers.py
beetsplug/beetmatch/common/logger.py
beetsplug/beetmatch/common/musly.py
beetsplug/beetmatch/feature/__init__.py
beetsplug/beetmatch/feature/jukebox/__init__.py
beetsplug/beetmatch/feature/jukebox/jukebox.py
beetsplug/beetmatch/feature/jukebox/jukebox_command.py
beetsplug/beetmatch/feature/jukebox/jukebox_config.py
beetsplug/beetmatch/feature/jukebox/jukebox_updater.py
beetsplug/beetmatch/feature/playlist/__init__.py
beetsplug/beetmatch/feature/playlist/cooldown.py
beetsplug/beetmatch/feature/playlist/library.py
beetsplug/beetmatch/feature/playlist/playlist_command.py
beetsplug/beetmatch/feature/playlist/playlist_config.py
beetsplug/beetmatch/feature/playlist/playlist_generator.py
beetsplug/beetmatch/feature/playlist/playlist_script.py
beetsplug/beetmatch/feature/playlist/track_attribute.py
beetsplug/beetmatch/feature/playlist/track_selector.py
beetsplug/beetmatch/feature/playlist/distances/__init__.py
beetsplug/beetmatch/feature/playlist/distances/bpm.py
beetsplug/beetmatch/feature/playlist/distances/distance.py
beetsplug/beetmatch/feature/playlist/distances/euclidean.py
beetsplug/beetmatch/feature/playlist/distances/musly.py
beetsplug/beetmatch/feature/playlist/distances/set.py
beetsplug/beetmatch/feature/playlist/distances/tonal.py
beetsplug/beetmatch/feature/playlist/distances/value.py
beetsplug/beetmatch/feature/playlist/distances/year.py
beets_beetmatch-0.3.2.dist-info/LICENSE.txt
beets_beetmatch-0.3.2.dist-info/METADATA
beets_beetmatch-0.3.2.dist-info/WHEEL
beets_beetmatch-0.3.2.dist-info/top_level.txt
beets_beetmatch-0.3.2.dist-info/RECORD
