Metadata-Version: 2.1
Name: beets-beetmatch
Version: 0.3.2
Summary: beets plugin for generating playlists of songs that somehow match
Author-email: Andreas Bannach <andreas@borntohula.de>
License: MIT License
Project-URL: Repository, https://github.com/andban/beets-beetmatch.git
Project-URL: Issues, https://github.com/andban/beets-beetmatch/issues
Keywords: beets
Platform: ALL
Classifier: Development Status :: 3 - Alpha
Classifier: Topic :: Multimedia :: Sound/Audio
Classifier: License :: OSI Approved :: MIT License
Classifier: Environment :: Console
Classifier: Programming Language :: Python :: 3
Classifier: Programming Language :: Python :: 3.9
Classifier: Programming Language :: Python :: 3.10
Classifier: Programming Language :: Python :: 3.11
Classifier: Programming Language :: Python :: 3.12
Requires-Python: >=3.9
License-File: LICENSE.txt
Requires-Dist: beets >=1.6.0
Provides-Extra: dev
Requires-Dist: pytest <8.4.0,>=8.3.3 ; extra == 'dev'
Requires-Dist: pytest-cov <6.1,>=6.0 ; extra == 'dev'
Requires-Dist: ruff <0.8.0,>=0.6.9 ; extra == 'dev'
Provides-Extra: musly
Requires-Dist: pymusly <2.0.0,>=1.0.3 ; extra == 'musly'
